<?xml version="1.0" encoding="UTF-8"?>
<beans xmlns="http://www.springframework.org/schema/beans"
	xmlns:xsi="http://www.w3.org/2001/XMLSchema-instance"
	xmlns:context="http://www.springframework.org/schema/context"
	xmlns:p="http://www.springframework.org/schema/p"
	xsi:schemaLocation="http://www.springframework.org/schema/beans http://www.springframework.org/schema/beans/spring-beans.xsd
		http://www.springframework.org/schema/context http://www.springframework.org/schema/context/spring-context.xsd">
	
    <bean id="localConfigProperties" class="org.springframework.beans.factory.config.PropertiesFactoryBean">  
       <property name="locations">  
           <list>
               <value>classpath:/properties/global.properties</value>
               <value>classpath:/properties/app.properties</value>
               <value>classpath:/properties/redis.properties</value>
           </list>
       </property>
       <property name="ignoreResourceNotFound" value="true"/>
    </bean>
		
	<bean id="cfgConfigProperties" class="com.taobao.diamond.extend.ExtendPropertiesFactoryBean">
        <property name="configs">
            <list>
                <!-- groupId  dataId -->
                <value>common, db</value>
                <value>common, redis</value>
            </list>
        </property>
        <property name="ignoreResourceNotFound" value="true"/>
        <property name="printCfgResults" value="true"/>
    </bean>
    
    <bean id="sysProperty" class="org.springframework.beans.factory.config.PreferencesPlaceholderConfigurer">
        <property name="propertiesArray">
           <list>
           		<!-- 按顺序加载， 若有重复，后者覆盖前者   -->
               	<ref bean="cfgConfigProperties"/>
               	<ref bean="localConfigProperties"/>
           </list>  
       </property>
    </bean>
	
</beans>
